azw3/CalibreUtils.py
azw3/__init__.py
azw3_converter-1.1.dist-info/METADATA
azw3_converter-1.1.dist-info/WHEEL
azw3_converter-1.1.dist-info/top_level.txt
azw3_converter-1.1.dist-info/RECORD
